{
  "variants": {
    "type=bottom,illuminated=false": {
      "model": "underground_overhaul:block/rock_salt_slab"
    },
    "type=double,illuminated=false": {
      "model": "underground_overhaul:block/rock_salt_block"
    },
    "type=top,illuminated=false": {
      "model": "underground_overhaul:block/rock_salt_slab_top"
    },
    "type=bottom,illuminated=true": {
      "model": "underground_overhaul:block/rock_salt_slab_lit"
    },
    "type=double,illuminated=true": {
      "model": "underground_overhaul:block/rock_salt_block_lit"
    },
    "type=top,illuminated=true": {
      "model": "underground_overhaul:block/rock_salt_slab_top_lit"
    }
  }
}